ntai/__init__.py
ntai/settings.py
ntai/bedtools/__init__.py
ntai/bedtools/functions.py
ntai/bedtools/subprocess.py
ntai/bedtools/utils.py
ntai/codex/__init__.py
ntai/codex/codex.py
ntai/codex/defaults.py
ntai/codex/test.py
ntai/codex/utils.py
ntai/codex/numpy/__init__.py
ntai/codex/numpy/codex.py
ntai/codex/numpy/defaults.py
ntai/codex/numpy/utils.py
ntai/fetch/__init__.py
ntai/fetch/utils.py
ntai/labeler/__init__.py
ntai/labeler/defaults.py
ntai/labeler/labeler.py
ntai/terminal/__init__.py
ntai/terminal/popen.py
ntai/terminal/tools.py
ntai/terminal/utils.py
ntai-1.0.0.dist-info/METADATA
ntai-1.0.0.dist-info/WHEEL
ntai-1.0.0.dist-info/top_level.txt
ntai-1.0.0.dist-info/RECORD
