Metadata-Version: 2.1
Name: ntai
Version: 1.0.0
Summary: Nucleotide A.I.
Home-page: https://gitlab.com/SumNeuron/ntai
Author: Sumner Magruder
Author-email: sumner.magruder@zmnh.uni-hamburg.de
License: UNKNOWN
Platform: UNKNOWN
Classifier: Programming Language :: Python :: 3.5
Classifier: License :: OSI Approved :: MIT License
Classifier: Operating System :: OS Independent
Requires-Dist: numba
Requires-Dist: lrng
Requires-Dist: numpy
